README.md
setup.py
bdk/__init__.py
bdk.egg-info/PKG-INFO
bdk.egg-info/SOURCES.txt
bdk.egg-info/dependency_links.txt
bdk.egg-info/entry_points.txt
bdk.egg-info/requires.txt
bdk.egg-info/top_level.txt
bdk/api/__init__.py
bdk/api/cli.py
bdk/common/__init__.py
bdk/common/interfaces.py
bdk/core/__init__.py
bdk/core/core.py
bdk/core/config/__init__.py
bdk/core/config/__init__.pyc
bdk/core/config/bdk_config_sample.yaml
bdk/core/config/dynamic_options.py
bdk/core/config/dynamic_options.pyc
bdk/core/config/fastlane_config_sample.yaml
bdk/core/config/schema.yaml
bdk/executors/__init__.py
bdk/executors/universal.py
bdk/executors/volta.py
bdk/executors/yandextank.py