Metadata-Version: 1.0
Name: bdk
Version: 0.0.13
Summary: Task manager
Home-page: https://github.com/yandex-load/bdk
Author: Yandex-load team
Author-email: load@yandex-team.ru
License: UNKNOWN
Platform: UNKNOWN
